odoo/addons/edi_purchase_oca/README.rst
odoo/addons/edi_purchase_oca/__init__.py
odoo/addons/edi_purchase_oca/__manifest__.py
odoo/addons/edi_purchase_oca/i18n/edi_purchase_oca.pot
odoo/addons/edi_purchase_oca/models/__init__.py
odoo/addons/edi_purchase_oca/models/purchase_order.py
odoo/addons/edi_purchase_oca/readme/CONTRIBUTORS.rst
odoo/addons/edi_purchase_oca/readme/DESCRIPTION.rst
odoo/addons/edi_purchase_oca/static/description/icon.png
odoo/addons/edi_purchase_oca/static/description/index.html
odoo/addons/edi_purchase_oca/views/edi_exchange_record_views.xml
odoo/addons/edi_purchase_oca/views/purchase_order_views.xml
odoo13_addon_edi_purchase_oca-13.0.1.0.1.dev3.dist-info/METADATA
odoo13_addon_edi_purchase_oca-13.0.1.0.1.dev3.dist-info/WHEEL
odoo13_addon_edi_purchase_oca-13.0.1.0.1.dev3.dist-info/top_level.txt
odoo13_addon_edi_purchase_oca-13.0.1.0.1.dev3.dist-info/RECORD
